<?xml version="1.0" encoding="utf-8" ?><dwsync><file name="jquery-ui-timepicker-af.js" server="greatgraphicdesigns.com/public_html/" local="3472555802" remote="319783739143509208" Dst="-1" /><file name="jquery-ui-timepicker-bg.js" server="greatgraphicdesigns.com/public_html/" local="3472555802" remote="319783739143509208" Dst="-1" /><file name="jquery-ui-timepicker-ca.js" server="greatgraphicdesigns.com/public_html/" local="3472555802" remote="319783739143509208" Dst="-1" /><file name="jquery-ui-timepicker-cs.js" server="greatgraphicdesigns.com/public_html/" local="3472555802" remote="319783739143509208" Dst="-1" /><file name="jquery-ui-timepicker-de.js" server="greatgraphicdesigns.com/public_html/" local="3472555802" remote="319783739143509208" Dst="-1" /><file name="jquery-ui-timepicker-el.js" server="greatgraphicdesigns.com/public_html/" local="3472555802" remote="319783739143509208" Dst="-1" /><file name="jquery-ui-timepicker-es.js" server="greatgraphicdesigns.com/public_html/" local="3472555802" remote="319783739143509208" Dst="-1" /><file name="jquery-ui-timepicker-fi.js" server="greatgraphicdesigns.com/public_html/" local="3472555802" remote="319783739143509208" Dst="-1" /><file name="jquery-ui-timepicker-et.js" server="greatgraphicdesigns.com/public_html/" local="3472555802" remote="319783739143509208" Dst="-1" /><file name="jquery-ui-timepicker-eu.js" server="greatgraphicdesigns.com/public_html/" local="3472555802" remote="319783739143509208" Dst="-1" /><file name="jquery-ui-timepicker-fr.js" server="greatgraphicdesigns.com/public_html/" local="3472555802" remote="319783739143509208" Dst="-1" /><file name="jquery-ui-timepicker-gl.js" server="greatgraphicdesigns.com/public_html/" local="3472555802" remote="319783739143509208" Dst="-1" /><file name="jquery-ui-timepicker-he.js" server="greatgraphicdesigns.com/public_html/" local="3472555802" remote="319783739143509208" Dst="-1" /><file name="jquery-ui-timepicker-hu.js" server="greatgraphicdesigns.com/public_html/" local="3472555802" remote="319783739143509208" Dst="-1" /><file name="jquery-ui-timepicker-id.js" server="greatgraphicdesigns.com/public_html/" local="3472555802" remote="319783739143509208" Dst="-1" /><file name="jquery-ui-timepicker-it.js" server="greatgraphicdesigns.com/public_html/" local="3472555802" remote="319783739143509208" Dst="-1" /><file name="jquery-ui-timepicker-ja.js" server="greatgraphicdesigns.com/public_html/" local="3472555802" remote="319783739143509208" Dst="-1" /><file name="jquery-ui-timepicker-ko.js" server="greatgraphicdesigns.com/public_html/" local="3472555802" remote="319783739143509208" Dst="-1" /><file name="jquery-ui-timepicker-lt.js" server="greatgraphicdesigns.com/public_html/" local="3472555802" remote="319783739143509208" Dst="-1" /><file name="jquery-ui-timepicker-nl.js" server="greatgraphicdesigns.com/public_html/" local="3472555802" remote="319783739143509208" Dst="-1" /><file name="jquery-ui-timepicker-pl.js" server="greatgraphicdesigns.com/public_html/" local="3472555802" remote="319783739143509208" Dst="-1" /><file name="jquery-ui-timepicker-no.js" server="greatgraphicdesigns.com/public_html/" local="3472555802" remote="319783739143509208" Dst="-1" /><file name="jquery-ui-timepicker-ro.js" server="greatgraphicdesigns.com/public_html/" local="3472555802" remote="319783739143509208" Dst="-1" /><file name="jquery-ui-timepicker-pt-BR.js" server="greatgraphicdesigns.com/public_html/" local="3472555802" remote="319783739143509208" Dst="-1" /><file name="jquery-ui-timepicker-pt.js" server="greatgraphicdesigns.com/public_html/" local="3472555802" remote="319783739143509208" Dst="-1" /><file name="jquery-ui-timepicker-ru.js" server="greatgraphicdesigns.com/public_html/" local="3472555802" remote="319783739143509208" Dst="-1" /><file name="jquery-ui-timepicker-sk.js" server="greatgraphicdesigns.com/public_html/" local="3472555802" remote="319783739143509208" Dst="-1" /><file name="jquery-ui-timepicker-sv.js" server="greatgraphicdesigns.com/public_html/" local="3472555802" remote="319783739143509208" Dst="-1" /><file name="jquery-ui-timepicker-th.js" server="greatgraphicdesigns.com/public_html/" local="3472555802" remote="319783739143509208" Dst="-1" /><file name="jquery-ui-timepicker-tr.js" server="greatgraphicdesigns.com/public_html/" local="3472555802" remote="319783739143509208" Dst="-1" /><file name="jquery-ui-timepicker-uk.js" server="greatgraphicdesigns.com/public_html/" local="3472555802" remote="319783739143509208" Dst="-1" /><file name="jquery-ui-timepicker-vi.js" server="greatgraphicdesigns.com/public_html/" local="3472555802" remote="319783739143509208" Dst="-1" /><file name="jquery-ui-timepicker-zh-CN.js" server="greatgraphicdesigns.com/public_html/" local="3472555802" remote="319783739143509208" Dst="-1" /><file name="jquery-ui-timepicker-zh-TW.js" server="greatgraphicdesigns.com/public_html/" local="3472555802" remote="319783739143509208" Dst="-1" /><file name="jquery-ui-timepicker-af.js" server="zacharynicholas.com/public_html/" local="3472555802" remote="319783739145496888" Dst="-1" /><file name="jquery-ui-timepicker-bg.js" server="zacharynicholas.com/public_html/" local="3472555802" remote="319783739145496888" Dst="-1" /><file name="jquery-ui-timepicker-ca.js" server="zacharynicholas.com/public_html/" local="3472555802" remote="319783739145496888" Dst="-1" /><file name="jquery-ui-timepicker-cs.js" server="zacharynicholas.com/public_html/" local="3472555802" remote="319783739145496888" Dst="-1" /><file name="jquery-ui-timepicker-de.js" server="zacharynicholas.com/public_html/" local="3472555802" remote="319783739145496888" Dst="-1" /><file name="jquery-ui-timepicker-el.js" server="zacharynicholas.com/public_html/" local="3472555802" remote="319783739145496888" Dst="-1" /><file name="jquery-ui-timepicker-es.js" server="zacharynicholas.com/public_html/" local="3472555802" remote="319783739145496888" Dst="-1" /><file name="jquery-ui-timepicker-et.js" server="zacharynicholas.com/public_html/" local="3472555802" remote="319783739145496888" Dst="-1" /><file name="jquery-ui-timepicker-eu.js" server="zacharynicholas.com/public_html/" local="3472555802" remote="319783739145496888" Dst="-1" /><file name="jquery-ui-timepicker-fi.js" server="zacharynicholas.com/public_html/" local="3472555802" remote="319783739145496888" Dst="-1" /><file name="jquery-ui-timepicker-fr.js" server="zacharynicholas.com/public_html/" local="3472555802" remote="319783739145496888" Dst="-1" /><file name="jquery-ui-timepicker-he.js" server="zacharynicholas.com/public_html/" local="3472555802" remote="319783739145496888" Dst="-1" /><file name="jquery-ui-timepicker-gl.js" server="zacharynicholas.com/public_html/" local="3472555802" remote="319783739145496888" Dst="-1" /><file name="jquery-ui-timepicker-it.js" server="zacharynicholas.com/public_html/" local="3472555802" remote="319783739145496888" Dst="-1" /><file name="jquery-ui-timepicker-hu.js" server="zacharynicholas.com/public_html/" local="3472555802" remote="319783739145496888" Dst="-1" /><file name="jquery-ui-timepicker-id.js" server="zacharynicholas.com/public_html/" local="3472555802" remote="319783739145496888" Dst="-1" /><file name="jquery-ui-timepicker-ko.js" server="zacharynicholas.com/public_html/" local="3472555802" remote="319783739145496888" Dst="-1" /><file name="jquery-ui-timepicker-lt.js" server="zacharynicholas.com/public_html/" local="3472555802" remote="319783739145496888" Dst="-1" /><file name="jquery-ui-timepicker-ja.js" server="zacharynicholas.com/public_html/" local="3472555802" remote="319783739145496888" Dst="-1" /><file name="jquery-ui-timepicker-nl.js" server="zacharynicholas.com/public_html/" local="3472555802" remote="319783739145496888" Dst="-1" /><file name="jquery-ui-timepicker-no.js" server="zacharynicholas.com/public_html/" local="3472555802" remote="319783739145496888" Dst="-1" /><file name="jquery-ui-timepicker-pl.js" server="zacharynicholas.com/public_html/" local="3472555802" remote="319783739145496888" Dst="-1" /><file name="jquery-ui-timepicker-pt.js" server="zacharynicholas.com/public_html/" local="3472555802" remote="319783739145496888" Dst="-1" /><file name="jquery-ui-timepicker-pt-BR.js" server="zacharynicholas.com/public_html/" local="3472555802" remote="319783739145496888" Dst="-1" /><file name="jquery-ui-timepicker-ro.js" server="zacharynicholas.com/public_html/" local="3472555802" remote="319783739145496888" Dst="-1" /><file name="jquery-ui-timepicker-ru.js" server="zacharynicholas.com/public_html/" local="3472555802" remote="319783739145496888" Dst="-1" /><file name="jquery-ui-timepicker-sk.js" server="zacharynicholas.com/public_html/" local="3472555802" remote="319783739145496888" Dst="-1" /><file name="jquery-ui-timepicker-sv.js" server="zacharynicholas.com/public_html/" local="3472555802" remote="319783739145496888" Dst="-1" /><file name="jquery-ui-timepicker-uk.js" server="zacharynicholas.com/public_html/" local="3472555802" remote="319783739145496888" Dst="-1" /><file name="jquery-ui-timepicker-tr.js" server="zacharynicholas.com/public_html/" local="3472555802" remote="319783739145496888" Dst="-1" /><file name="jquery-ui-timepicker-th.js" server="zacharynicholas.com/public_html/" local="3472555802" remote="319783739145496888" Dst="-1" /><file name="jquery-ui-timepicker-vi.js" server="zacharynicholas.com/public_html/" local="3472555802" remote="319783739145496888" Dst="-1" /><file name="jquery-ui-timepicker-zh-CN.js" server="zacharynicholas.com/public_html/" local="3472555802" remote="319783739145496888" Dst="-1" /><file name="jquery-ui-timepicker-zh-TW.js" server="zacharynicholas.com/public_html/" local="3472555802" remote="319783739145496888" Dst="-1" /><file name="jquery-ui-timepicker-af.js" server="zaknicholas.com/public_html/zacharynicholas.com/" local="3472555802" remote="3527531400" Dst="-1" /><file name="jquery-ui-timepicker-ca.js" server="zaknicholas.com/public_html/zacharynicholas.com/" local="3472555802" remote="3527531400" Dst="-1" /><file name="jquery-ui-timepicker-cs.js" server="zaknicholas.com/public_html/zacharynicholas.com/" local="3472555802" remote="3527531400" Dst="-1" /><file name="jquery-ui-timepicker-bg.js" server="zaknicholas.com/public_html/zacharynicholas.com/" local="3472555802" remote="3527531400" Dst="-1" /><file name="jquery-ui-timepicker-de.js" server="zaknicholas.com/public_html/zacharynicholas.com/" local="3472555802" remote="3527531400" Dst="-1" /><file name="jquery-ui-timepicker-el.js" server="zaknicholas.com/public_html/zacharynicholas.com/" local="3472555802" remote="3527531400" Dst="-1" /><file name="jquery-ui-timepicker-es.js" server="zaknicholas.com/public_html/zacharynicholas.com/" local="3472555802" remote="3527531400" Dst="-1" /><file name="jquery-ui-timepicker-et.js" server="zaknicholas.com/public_html/zacharynicholas.com/" local="3472555802" remote="3527531400" Dst="-1" /><file name="jquery-ui-timepicker-eu.js" server="zaknicholas.com/public_html/zacharynicholas.com/" local="3472555802" remote="3527531400" Dst="-1" /><file name="jquery-ui-timepicker-fi.js" server="zaknicholas.com/public_html/zacharynicholas.com/" local="3472555802" remote="3527531400" Dst="-1" /><file name="jquery-ui-timepicker-fr.js" server="zaknicholas.com/public_html/zacharynicholas.com/" local="3472555802" remote="3527531400" Dst="-1" /><file name="jquery-ui-timepicker-gl.js" server="zaknicholas.com/public_html/zacharynicholas.com/" local="3472555802" remote="3527531400" Dst="-1" /><file name="jquery-ui-timepicker-he.js" server="zaknicholas.com/public_html/zacharynicholas.com/" local="3472555802" remote="3527531400" Dst="-1" /><file name="jquery-ui-timepicker-hu.js" server="zaknicholas.com/public_html/zacharynicholas.com/" local="3472555802" remote="3527531400" Dst="-1" /><file name="jquery-ui-timepicker-id.js" server="zaknicholas.com/public_html/zacharynicholas.com/" local="3472555802" remote="3527531400" Dst="-1" /><file name="jquery-ui-timepicker-it.js" server="zaknicholas.com/public_html/zacharynicholas.com/" local="3472555802" remote="3527531400" Dst="-1" /><file name="jquery-ui-timepicker-ja.js" server="zaknicholas.com/public_html/zacharynicholas.com/" local="3472555802" remote="3527531400" Dst="-1" /><file name="jquery-ui-timepicker-ko.js" server="zaknicholas.com/public_html/zacharynicholas.com/" local="3472555802" remote="3527531400" Dst="-1" /><file name="jquery-ui-timepicker-lt.js" server="zaknicholas.com/public_html/zacharynicholas.com/" local="3472555802" remote="3527531400" Dst="-1" /><file name="jquery-ui-timepicker-nl.js" server="zaknicholas.com/public_html/zacharynicholas.com/" local="3472555802" remote="3527531400" Dst="-1" /><file name="jquery-ui-timepicker-pl.js" server="zaknicholas.com/public_html/zacharynicholas.com/" local="3472555802" remote="3527531400" Dst="-1" /><file name="jquery-ui-timepicker-no.js" server="zaknicholas.com/public_html/zacharynicholas.com/" local="3472555802" remote="3527531400" Dst="-1" /><file name="jquery-ui-timepicker-pt-BR.js" server="zaknicholas.com/public_html/zacharynicholas.com/" local="3472555802" remote="3527531400" Dst="-1" /><file name="jquery-ui-timepicker-pt.js" server="zaknicholas.com/public_html/zacharynicholas.com/" local="3472555802" remote="3527531400" Dst="-1" /><file name="jquery-ui-timepicker-ro.js" server="zaknicholas.com/public_html/zacharynicholas.com/" local="3472555802" remote="3527531400" Dst="-1" /><file name="jquery-ui-timepicker-ru.js" server="zaknicholas.com/public_html/zacharynicholas.com/" local="3472555802" remote="3527531400" Dst="-1" /><file name="jquery-ui-timepicker-sv.js" server="zaknicholas.com/public_html/zacharynicholas.com/" local="3472555802" remote="3527531400" Dst="-1" /><file name="jquery-ui-timepicker-sk.js" server="zaknicholas.com/public_html/zacharynicholas.com/" local="3472555802" remote="3527531400" Dst="-1" /><file name="jquery-ui-timepicker-th.js" server="zaknicholas.com/public_html/zacharynicholas.com/" local="3472555802" remote="3527531400" Dst="-1" /><file name="jquery-ui-timepicker-uk.js" server="zaknicholas.com/public_html/zacharynicholas.com/" local="3472555802" remote="3527531400" Dst="-1" /><file name="jquery-ui-timepicker-vi.js" server="zaknicholas.com/public_html/zacharynicholas.com/" local="3472555802" remote="3527531400" Dst="-1" /><file name="jquery-ui-timepicker-tr.js" server="zaknicholas.com/public_html/zacharynicholas.com/" local="3472555802" remote="3527531400" Dst="-1" /><file name="jquery-ui-timepicker-zh-CN.js" server="zaknicholas.com/public_html/zacharynicholas.com/" local="3472555802" remote="3527531400" Dst="-1" /><file name="jquery-ui-timepicker-zh-TW.js" server="zaknicholas.com/public_html/zacharynicholas.com/" local="3472555802" remote="3527531400" Dst="-1" /></dwsync>